odoo/addons/pos_product_pack/README.rst
odoo/addons/pos_product_pack/__init__.py
odoo/addons/pos_product_pack/__manifest__.py
odoo/addons/pos_product_pack/i18n/it.po
odoo/addons/pos_product_pack/i18n/pos_product_pack.pot
odoo/addons/pos_product_pack/models/__init__.py
odoo/addons/pos_product_pack/models/pos_order_line.py
odoo/addons/pos_product_pack/readme/CONTRIBUTORS.rst
odoo/addons/pos_product_pack/readme/DESCRIPTION.rst
odoo/addons/pos_product_pack/readme/ROADMAP.rst
odoo/addons/pos_product_pack/readme/USAGE.rst
odoo/addons/pos_product_pack/static/description/icon.png
odoo/addons/pos_product_pack/static/description/index.html
odoo/addons/pos_product_pack/static/src/js/models.js
odoo/addons/pos_product_pack/views/pos_product_pack.xml
odoo14_addon_pos_product_pack-14.0.1.0.1.dev16.dist-info/METADATA
odoo14_addon_pos_product_pack-14.0.1.0.1.dev16.dist-info/WHEEL
odoo14_addon_pos_product_pack-14.0.1.0.1.dev16.dist-info/top_level.txt
odoo14_addon_pos_product_pack-14.0.1.0.1.dev16.dist-info/RECORD
